src/__init__.py
src/base/__init__.py
src/base/main.py
src/lib/__init__.py
src/lib/functions.py
melia-0.0.3.dist-info/LICENSE
melia-0.0.3.dist-info/METADATA
melia-0.0.3.dist-info/WHEEL
melia-0.0.3.dist-info/top_level.txt
melia-0.0.3.dist-info/RECORD
