Metadata-Version: 2.1
Name: melia
Version: 0.0.3
Summary: Meta-linguistic abstractions
Home-page: UNKNOWN
Author: dindefi
Author-email: dindefi@gmail.com
License: Apache 2.0
Platform: UNKNOWN
